AUTHORS.rst
CONTRIBUTING.rst
HISTORY.rst
LICENSE
MANIFEST.in
README.rst
setup.cfg
setup.py
docs/Makefile
docs/authors.rst
docs/conf.py
docs/contributing.rst
docs/history.rst
docs/index.rst
docs/installation.rst
docs/make.bat
docs/readme.rst
docs/usage.rst
sras/__init__.py
sras/cli.py
sras/sras.py
sras.egg-info/PKG-INFO
sras.egg-info/SOURCES.txt
sras.egg-info/dependency_links.txt
sras.egg-info/entry_points.txt
sras.egg-info/not-zip-safe
sras.egg-info/requires.txt
sras.egg-info/top_level.txt
tests/__init__.py
tests/test_sras.py