Metadata-Version: 1.1
Name: sras
Version: 0.1.0
Summary: A python package with list of helpful modules for report automation and analytics.
Home-page: https://github.com/SreenathYettapu/sras
Author: Sreenath Reddy Yettapu
Author-email: sreenath.yettapu@outlook.com
License: MIT license
Keywords: sras
Platform: UNKNOWN
Classifier: Development Status :: 2 - Pre-Alpha
Classifier: Intended Audience :: Developers
Classifier: License :: OSI Approved :: MIT License
Classifier: Natural Language :: English
Classifier: Programming Language :: Python :: 2
Classifier: Programming Language :: Python :: 2.6
Classifier: Programming Language :: Python :: 2.7
Classifier: Programming Language :: Python :: 3
Classifier: Programming Language :: Python :: 3.3
Classifier: Programming Language :: Python :: 3.4
Classifier: Programming Language :: Python :: 3.5
